.gitignore
LICENSE.txt
MANIFEST.in
README.md
setup.py
doc/Doxyfile
doc/index.dox
doc/officegenerator.png
doc/officegenerator.svg
locale/es.po
locale/officegenerator.pot
officegenerator/__init__.py
officegenerator/casts.py
officegenerator/commons.py
officegenerator/datetime_functions.py
officegenerator/decorators.py
officegenerator/demo.py
officegenerator/github.py
officegenerator/libmanagers.py
officegenerator/libodfgenerator.py
officegenerator/libxlsxgenerator.py
officegenerator/odf2xml.py
officegenerator/standard_sheets.py
officegenerator/xlsx2xml.py
officegenerator.egg-info/PKG-INFO
officegenerator.egg-info/SOURCES.txt
officegenerator.egg-info/dependency_links.txt
officegenerator.egg-info/entry_points.txt
officegenerator.egg-info/not-zip-safe
officegenerator.egg-info/requires.txt
officegenerator.egg-info/top_level.txt
officegenerator/images/crown.png
officegenerator/locale/es/LC_MESSAGES/officegenerator.mo
officegenerator/objects/__init__.py
officegenerator/objects/currency.py
officegenerator/objects/formula.py
officegenerator/objects/percentage.py
officegenerator/templates/odt/standard.odt
officegenerator/tests/__init__.py
officegenerator/tests/test_commons.py
officegenerator/tests/test_demo.py
officegenerator/tests/test_libodfgenerator.py
officegenerator/tests/test_libxlsxgenerator.py