Metadata-Version: 2.1
Name: officegenerator
Version: 1.28.0
Summary: Python module to read and write LibreOffice and MS Office files
Home-page: https://officegenerator.sourceforge.io/
Author: Turulomio
Author-email: turulomio@yahoo.es
License: GPL-3
Keywords: office generator
Platform: UNKNOWN
Classifier: Development Status :: 4 - Beta
Classifier: Intended Audience :: Developers
Classifier: Topic :: Software Development :: Build Tools
Classifier: License :: OSI Approved :: GNU General Public License v3 (GPLv3)
Classifier: Programming Language :: Python :: 3
